setup.py
subheadings.py
nose_subheadings_plugin.egg-info/PKG-INFO
nose_subheadings_plugin.egg-info/SOURCES.txt
nose_subheadings_plugin.egg-info/dependency_links.txt
nose_subheadings_plugin.egg-info/entry_points.txt
nose_subheadings_plugin.egg-info/requires.txt
nose_subheadings_plugin.egg-info/top_level.txt