Metadata-Version: 1.0
Name: nose-subheadings-plugin
Version: 0.1
Summary: Subheadings for nose --verbosity=2 output
Home-page: https://github.com/akaihola/nose-subheadings-plugin
Author: Antti Kaihola
Author-email: akaihol+nose@ambitone.com
License: BSD
Keywords: test nosetests nose nosetest output console subheading
Platform: UNKNOWN
Classifier: Development Status :: 4 - Beta
Classifier: Intended Audience :: Developers
Classifier: License :: OSI Approved :: BSD License
Classifier: Operating System :: OS Independent
Classifier: Programming Language :: Python
Classifier: Topic :: Software Development :: Libraries :: Python Modules
Classifier: Topic :: Software Development :: Testing
